LICENSE
MANIFEST.in
README.md
requirements.txt
setup.cfg
setup.py
cpe_utils/__init__.py
cpe_utils.egg-info/PKG-INFO
cpe_utils.egg-info/SOURCES.txt
cpe_utils.egg-info/dependency_links.txt
cpe_utils.egg-info/top_level.txt
tests/test_basic.py